{
  "project_info": {
    "project_number": "1042744839800",
    "project_id": "bahari-scratch",
    "storage_bucket": "bahari-scratch.appspot.com"
  },
  "client": [
    {
      "client_info": {
        "mobilesdk_app_id": "1:1042744839800:android:8b75bdf87630ad9077a78d",
        "android_client_info": {
          "package_name": "co.tz.scratch.bahari"
        }
      },
      "oauth_client": [
        {
          "client_id": "1042744839800-oompv1nor9erqedb5hs2d55bit3fea74.apps.googleusercontent.com",
          "client_type": 3
        }
      ],
      "api_key": [
        {
          "current_key": "AIzaSyAAgbOrgHvZKfMcnbb8hg_3x11zeU9n4qo"
        }
      ],
      "services": {
        "appinvite_service": {
          "other_platform_oauth_client": [
            {
              "client_id": "1042744839800-oompv1nor9erqedb5hs2d55bit3fea74.apps.googleusercontent.com",
              "client_type": 3
            }
          ]
        }
      }
    }
  ],
  "configuration_version": "1"
}